<?xml version='1.0' encoding='UTF-8'?>
<mdRecord 
            xmlns='http://dplava.lib.virginia.edu'
            xmlns:xsi='http://www.w3.org/2001/XMLSchema-instance'
            xmlns:dc='http://purl.org/dc/elements/1.1/'
            xmlns:dcterms='http://purl.org/dc/terms/'
            xmlns:rdf='http://www.w3.org/1999/02/22-rdf-syntax-ns#'
            xmlns:edm='http://www.europeana.eu/schemas/edm/'
            xsi:schemaLocation='http://dplava.lib.virginia.edu dplava.xsd'
          >
	<dcterms:identifier>iai001447</dcterms:identifier>
	<dcterms:isPartOf>International Association for Identification. Records</dcterms:isPartOf>
	<dcterms:title>Prints Test; 01 of 01</dcterms:title>
	<dcterms:temporal>2018-07-16</dcterms:temporal>
	<dcterms:description>3. Doepner/Faulds--NotesItems 1-134--Clippings ScrapbookPage 36 (front of added page); "Finger-Prints Test"; A man named John was found in Salford, and denied being a criminal even though his fingerprints said otherwise. A trial at the Sessions will be held.; no pub info; DF 654</dcterms:description>
	<dcterms:subject>Evidence, Criminal</dcterms:subject>
	<dcterms:subject>Fingerprints</dcterms:subject>
	<dcterms:rights>http://rightsstatements.org/vocab/UND/1.0/</dcterms:rights>
	<dcterms:provenance>West Virginia University Libraries</dcterms:provenance>
	<edm:isShownAt>http://iai.lib.wvu.edu/record/iai001447</edm:isShownAt>
	<edm:preview>https://iai.lib.wvu.edu/thumb/iai001447.jpg</edm:preview>
</mdRecord>
