<?xml version='1.0' encoding='UTF-8'?>
<mdRecord 
            xmlns='http://dplava.lib.virginia.edu'
            xmlns:xsi='http://www.w3.org/2001/XMLSchema-instance'
            xmlns:dc='http://purl.org/dc/elements/1.1/'
            xmlns:dcterms='http://purl.org/dc/terms/'
            xmlns:rdf='http://www.w3.org/1999/02/22-rdf-syntax-ns#'
            xmlns:edm='http://www.europeana.eu/schemas/edm/'
            xsi:schemaLocation='http://dplava.lib.virginia.edu dplava.xsd'
          >
	<dcterms:identifier>iai001715</dcterms:identifier>
	<dcterms:isPartOf>International Association for Identification. Records</dcterms:isPartOf>
	<dcterms:title>Herschel, artifact; 01 of 01</dcterms:title>
	<dcterms:temporal>2018-07-16</dcterms:temporal>
	<dcterms:description>4. Forensic Identification Reference Material (FIRM)Items 4-26, Fingerprinting--Fiorenza (Multiple articles, notes, news clippings found together in labeled binder.)A photograph copy of an artifact from the New York Institute of Criminology which shows a palmprint and a written agreement in English and what appears to be Hindi. It states it is between W.J. Herschel and R&amp;#257;jyadhar Kon&amp;#257;i in 1858. Typewritten information regards the IAI conference at which it was presented in 1957.; 1 item.</dcterms:description>
	<dcterms:subject>Herschel, William, Sir, 17381822</dcterms:subject>
	<dcterms:subject>International Association for Identification</dcterms:subject>
	<dcterms:subject>Palmprints</dcterms:subject>
	<dcterms:rights>http://rightsstatements.org/vocab/UND/1.0/</dcterms:rights>
	<dcterms:provenance>West Virginia University Libraries</dcterms:provenance>
	<edm:isShownAt>http://iai.lib.wvu.edu/record/iai001715</edm:isShownAt>
	<edm:preview>https://iai.lib.wvu.edu/thumb/iai001715.jpg</edm:preview>
</mdRecord>
