<?xml version='1.0' encoding='UTF-8'?>
<mdRecord 
          xmlns='http://dplava.lib.virginia.edu'
          xmlns:xsi='http://www.w3.org/2001/XMLSchema-instance'
          xmlns:dc='http://purl.org/dc/elements/1.1/'
          xmlns:dcterms='http://purl.org/dc/terms/'
          xmlns:rdf='http://www.w3.org/1999/02/22-rdf-syntax-ns#'
          xmlns:edm='http://www.europeana.eu/schemas/edm/'
          xsi:schemaLocation='http://dplava.lib.virginia.edu dplava.xsd'
        >
	<dcterms:identifier>ptp_0733</dcterms:identifier>
	<dcterms:isPartOf>Francis H. Pierpont Civil War Telegrams</dcterms:isPartOf>
	<dcterms:title>Curtin, Andrew G. to Pierpont, Francis H.</dcterms:title>
	<dcterms:created>1862-09-?? </dcterms:created>
	<dcterms:creator>Curtin, Andrew G.</dcterms:creator>
	<dcterms:description>Gov Peirpoint [Francis H. Pierpont] Wheeling Sept 1862.   By Telegraph from Harrisburg 1862.   In the present emergency would it not be well that the loyal Governors should meet at some point in the border states to take measures for the more active support of the government an immediate answer is requested that as early a day as possible may be named [page 2] for the meeting if approved AG Curtin  53G121pd</dcterms:description>
	<dcterms:extent>page 1 of 2; leaf 1 of 1</dcterms:extent>
	<dcterms:subject>Curtin, Andrew G.</dcterms:subject>
	<dcterms:subject>Harrisburg, Pennsylvania</dcterms:subject>
	<dcterms:subject>Wheeling, (West) Virginia</dcterms:subject>
	<dcterms:subject>Pierpont, Francis H.</dcterms:subject>
	<dcterms:spatial>Harrisburg, Pennsylvania</dcterms:spatial>
	<dcterms:spatial>Wheeling, (West) Virginia</dcterms:spatial>
	<dcterms:rights>http://rightsstatements.org/vocab/NoC-US/1.0/</dcterms:rights>
	<dcterms:provenance>West Virginia University Libraries</dcterms:provenance>
	<edm:isShownAt>https://civilwarwv.lib.wvu.edu/record/ptp_0733</edm:isShownAt>
	<edm:preview>https://civilwarwv.lib.wvu.edu/image/ptp_0733.jpg</edm:preview>
</mdRecord>
