<?xml version='1.0' encoding='UTF-8'?>
<mdRecord 
          xmlns='http://dplava.lib.virginia.edu'
          xmlns:xsi='http://www.w3.org/2001/XMLSchema-instance'
          xmlns:dc='http://purl.org/dc/elements/1.1/'
          xmlns:dcterms='http://purl.org/dc/terms/'
          xmlns:rdf='http://www.w3.org/1999/02/22-rdf-syntax-ns#'
          xmlns:edm='http://www.europeana.eu/schemas/edm/'
          xsi:schemaLocation='http://dplava.lib.virginia.edu dplava.xsd'
        >
	<dcterms:identifier>ptp_0285</dcterms:identifier>
	<dcterms:isPartOf>Francis H. Pierpont Civil War Telegrams</dcterms:isPartOf>
	<dcterms:title>Bisbee, William H. to Bolles, William M.; Paxton, Francis M.</dcterms:title>
	<dcterms:created>1861-09-06</dcterms:created>
	<dcterms:creator>Bisbee, William H.</dcterms:creator>
	<dcterms:description>Col Bolles or Paxton care Gov Peirpoint [Francis H. Pierpont] Wheeling Sept 6 1861.   By Telegraph from Marietta 6 1861.   Hamilton reports his company ready to move on Monday answer him in regard to transportation he is at Hamden Bisbee 19HW86pd</dcterms:description>
	<dcterms:extent>page 1 of 1; leaf 1 of 1</dcterms:extent>
	<dcterms:subject>Bisbee, William H.</dcterms:subject>
	<dcterms:subject>Marietta, Ohio</dcterms:subject>
	<dcterms:subject>Wheeling, (West) Virginia</dcterms:subject>
	<dcterms:subject>Bolles, William M.; Paxton, Francis M.</dcterms:subject>
	<dcterms:spatial>Marietta, Ohio</dcterms:spatial>
	<dcterms:spatial>Wheeling, (West) Virginia</dcterms:spatial>
	<dcterms:rights>http://rightsstatements.org/vocab/NoC-US/1.0/</dcterms:rights>
	<dcterms:provenance>West Virginia University Libraries</dcterms:provenance>
	<edm:isShownAt>https://civilwarwv.lib.wvu.edu/record/ptp_0285</edm:isShownAt>
	<edm:preview>https://civilwarwv.lib.wvu.edu/image/ptp_0285.jpg</edm:preview>
</mdRecord>
