<?xml version='1.0' encoding='UTF-8'?>
<mdRecord 
          xmlns='http://dplava.lib.virginia.edu'
          xmlns:xsi='http://www.w3.org/2001/XMLSchema-instance'
          xmlns:dc='http://purl.org/dc/elements/1.1/'
          xmlns:dcterms='http://purl.org/dc/terms/'
          xmlns:rdf='http://www.w3.org/1999/02/22-rdf-syntax-ns#'
          xmlns:edm='http://www.europeana.eu/schemas/edm/'
          xsi:schemaLocation='http://dplava.lib.virginia.edu dplava.xsd'
        >
	<dcterms:identifier>ptp_0335</dcterms:identifier>
	<dcterms:isPartOf>Francis H. Pierpont Civil War Telegrams</dcterms:isPartOf>
	<dcterms:title>Stanley, J. G. to Pierpont, Francis H.</dcterms:title>
	<dcterms:created>1861-09-14</dcterms:created>
	<dcterms:creator>Stanley, J. G.</dcterms:creator>
	<dcterms:description>Gov Peirpoint [Francis H. Pierpont] Wheeling Sept 14 1861.   By Telegraph from Camp Scott 1861.   It is understood by Genl Rosecrans that Genl Meigs has provided you &amp; placed in your charge a quantity of clothing camp &amp; infantry equipage for ten infantry &amp; one Cavalry regt if so please answer me at once J. G. Stanley Capt AQM 39D83pd</dcterms:description>
	<dcterms:extent>page 1 of 1; leaf 1 of 1</dcterms:extent>
	<dcterms:subject>Stanley, J. G.</dcterms:subject>
	<dcterms:subject>Camp Scott</dcterms:subject>
	<dcterms:subject>Wheeling, (West) Virginia</dcterms:subject>
	<dcterms:subject>Pierpont, Francis H.</dcterms:subject>
	<dcterms:spatial>Camp Scott</dcterms:spatial>
	<dcterms:spatial>Wheeling, (West) Virginia</dcterms:spatial>
	<dcterms:rights>http://rightsstatements.org/vocab/NoC-US/1.0/</dcterms:rights>
	<dcterms:provenance>West Virginia University Libraries</dcterms:provenance>
	<edm:isShownAt>https://civilwarwv.lib.wvu.edu/record/ptp_0335</edm:isShownAt>
	<edm:preview>https://civilwarwv.lib.wvu.edu/image/ptp_0335.jpg</edm:preview>
</mdRecord>
