<?xml version='1.0' encoding='UTF-8'?>
<mdRecord 
          xmlns='http://dplava.lib.virginia.edu'
          xmlns:xsi='http://www.w3.org/2001/XMLSchema-instance'
          xmlns:dc='http://purl.org/dc/elements/1.1/'
          xmlns:dcterms='http://purl.org/dc/terms/'
          xmlns:rdf='http://www.w3.org/1999/02/22-rdf-syntax-ns#'
          xmlns:edm='http://www.europeana.eu/schemas/edm/'
          xsi:schemaLocation='http://dplava.lib.virginia.edu dplava.xsd'
        >
	<dcterms:identifier>ptp_0067</dcterms:identifier>
	<dcterms:isPartOf>Francis H. Pierpont Civil War Telegrams</dcterms:isPartOf>
	<dcterms:title>Brakeley, A.; Brakeley J. to Micah, G. N. J.</dcterms:title>
	<dcterms:created>1861-07-12</dcterms:created>
	<dcterms:creator>Brakeley, A.; Brakeley J.</dcterms:creator>
	<dcterms:description>G N J Micah[?] Wheeling July 12 1861.   By Telegraph, from Rowlesburg 12 1860.  Can Civil Officers act Officially without taking oath prescribed by Wheeling Convention if they do are their acts valid.  J&amp;A Brakeley 19s62pd [page 2] J&amp;A Brakely [Brakeley] Rowlesburg July 12
</dcterms:description>
	<dcterms:extent>page 1 of 2; leaf 1 of 1</dcterms:extent>
	<dcterms:subject>Brakeley, A.; Brakeley J.</dcterms:subject>
	<dcterms:subject>Rowlesburg, (West) Virginia</dcterms:subject>
	<dcterms:subject>Wheeling, (West) Virginia</dcterms:subject>
	<dcterms:subject>Micah, G. N. J.</dcterms:subject>
	<dcterms:spatial>Rowlesburg, (West) Virginia</dcterms:spatial>
	<dcterms:spatial>Wheeling, (West) Virginia</dcterms:spatial>
	<dcterms:rights>http://rightsstatements.org/vocab/NoC-US/1.0/</dcterms:rights>
	<dcterms:provenance>West Virginia University Libraries</dcterms:provenance>
	<edm:isShownAt>https://civilwarwv.lib.wvu.edu/record/ptp_0067</edm:isShownAt>
	<edm:preview>https://civilwarwv.lib.wvu.edu/image/ptp_0067.jpg</edm:preview>
</mdRecord>
