<?xml version='1.0' encoding='UTF-8'?>
<mdRecord 
            xmlns='http://dplava.lib.virginia.edu'
            xmlns:xsi='http://www.w3.org/2001/XMLSchema-instance'
            xmlns:dc='http://purl.org/dc/elements/1.1/'
            xmlns:dcterms='http://purl.org/dc/terms/'
            xmlns:rdf='http://www.w3.org/1999/02/22-rdf-syntax-ns#'
            xmlns:edm='http://www.europeana.eu/schemas/edm/'
            xsi:schemaLocation='http://dplava.lib.virginia.edu dplava.xsd'
          >
	<dcterms:identifier>clarysville_00743</dcterms:identifier>
	<dcterms:isPartOf>Clarysville Hospital. Civil War Records of Samuel West, Physician</dcterms:isPartOf>
	<dcterms:title>Patient Record for Emerson, James </dcterms:title>
	<dcterms:created>1864-08-05</dcterms:created>
	<dcterms:spatial>Pennsylvania</dcterms:spatial>
	<dcterms:spatial>Lawrence Co., O [Lawrence County, Ohio]</dcterms:spatial>
	<dcterms:spatial>Symmes Run, O [Symmes Run, Ohio]</dcterms:spatial>
	<dcterms:description>Patient Name: Emerson, James Patient Age: 39. Marital Status: Married. Diagnosis: Chronic vascular disease of heart. Result: Transferred to US Genl Hospital Parkersburg 1864/09/24. </dcterms:description>
	<dcterms:subject>Emerson, James </dcterms:subject>
	<dcterms:subject>Chronic vascular disease of heart</dcterms:subject>
	<dcterms:subject>Private</dcterms:subject>
	<dcterms:subject>I</dcterms:subject>
	<dcterms:subject>9 VA Vols [9th West Virginia Volunteer Infantry]</dcterms:subject>
	<dcterms:subject>Pennsylvania</dcterms:subject>
	<dcterms:subject>Hospital Number 4053</dcterms:subject>
	<dcterms:type>Image</dcterms:type>
	<dcterms:rights>http://rightsstatements.org/vocab/UND/1.0/</dcterms:rights>
	<dcterms:provenance>West Virginia University Libraries</dcterms:provenance>
	<edm:isShownAt>http://clarysville.lib.wvu.edu/record/clarysville_00743</edm:isShownAt>
	<edm:preview>http://clarysville.lib.wvu.edu/image/front/clarysville_00743.jpg</edm:preview>
</mdRecord>
