<?xml version='1.0' encoding='UTF-8'?>
<mdRecord 
            xmlns='http://dplava.lib.virginia.edu'
            xmlns:xsi='http://www.w3.org/2001/XMLSchema-instance'
            xmlns:dc='http://purl.org/dc/elements/1.1/'
            xmlns:dcterms='http://purl.org/dc/terms/'
            xmlns:rdf='http://www.w3.org/1999/02/22-rdf-syntax-ns#'
            xmlns:edm='http://www.europeana.eu/schemas/edm/'
            xsi:schemaLocation='http://dplava.lib.virginia.edu dplava.xsd'
          >
	<dcterms:identifier>am2862_moore_0293</dcterms:identifier>
	<dcterms:isPartOf>Arch Moore Jr. &amp; Shelley Moore Archives</dcterms:isPartOf>
	<dcterms:title>Photograph of Congressman Moore with West Point Cadet Morris E. Brown, Jr. </dcterms:title>
	<dcterms:created>circa 1960/1966</dcterms:created>
	<dcterms:description>West Point Cadet Morris E. Brown, Jr. and Congressman Arch A. Moore, Jr. on the steps of the House Office Builidng in Washington during his visit to the Nation's Capitol. Brown was one of Congressman Moore's principal Academy appointments during the last session of Congress. </dcterms:description>
	<dcterms:subject>Brown, Morris E </dcterms:subject>
	<dcterms:subject>GovernorsWest Virginia </dcterms:subject>
	<dcterms:subject>LegislatorsUnited States</dcterms:subject>
	<dcterms:subject>Military </dcterms:subject>
	<dcterms:subject>Military cadets</dcterms:subject>
	<dcterms:subject>Military cadetsUnited States</dcterms:subject>
	<dcterms:subject>Moore, Arch A, Jr (Arch Alfred), 19232015</dcterms:subject>
	<dcterms:subject>United States Corps of Cadets</dcterms:subject>
	<dcterms:subject>United States Military Academy</dcterms:subject>
	<dcterms:publisher>West Virginia &amp; Regional History Center</dcterms:publisher>
	<dcterms:type>StillImage</dcterms:type>
	<dcterms:format>image/tiff</dcterms:format>
	<dcterms:source>A&amp;M 2862, Governor Arch A. Moore Jr. papers, West Virginia &amp; Regional History Center, West Virginia University Libraries</dcterms:source>
	<dcterms:language>English</dcterms:language>
	<dcterms:rights>http://rightsstatements.org/vocab/CNE/1.0/</dcterms:rights>
	<dcterms:provenance>West Virginia &amp; Regional History Center</dcterms:provenance>
	<edm:isShownAt>http://moore.lib.wvu.edu/catalog/am2862_moore_0293</edm:isShownAt>
	<edm:preview>https://moore.lib.wvu.edu/image/am2862_moore_0293.jpg</edm:preview>
</mdRecord>
